calculadora/__init__.py
calculadora/basica.py
calculadora/cientifica.py
calculadora/estadistica.py
paquete_hackademy-1.0.0.dist-info/METADATA
paquete_hackademy-1.0.0.dist-info/WHEEL
paquete_hackademy-1.0.0.dist-info/top_level.txt
paquete_hackademy-1.0.0.dist-info/RECORD
